{
    "__comment": "Made with TheDestruc7i0n's advancements generator: https://advancements.thedestruc7i0n.ca",
    "parent": "charlsensideas:root",
    "display": {
        "title": {
            "text": "Even Deeper",
            "color": "gold",
            "bold": true,
            "italic": false
        },
        "description": {
            "text": "Go to Tenebris",
            "color": "white"
        },
        "icon": {
            "item": "charlsensideas:cobbled_black_tourmaline_stone"
        },
        "frame": "task",
        "show_toast": true,
        "announce_to_chat": true,
        "hidden": false
    },
    "criteria": {
        "Trigger": {
            "trigger": "minecraft:changed_dimension",
            "conditions": {
                "from": "overworld",
                "to": "charlsensideas:tenebris"
            }
        }
    },
    "rewards": {
        "experience": 20
    }
}